tests/__init__.py
tests/test_zarr_jpeg2k.py
zarr_jpeg2k/__init__.py
zarr_jpeg2k/version.py
zarr_jpeg2k/zarr_jpeg2k.py
zarr_jpeg2k-0.1.0rc3.dist-info/LICENSE
zarr_jpeg2k-0.1.0rc3.dist-info/METADATA
zarr_jpeg2k-0.1.0rc3.dist-info/WHEEL
zarr_jpeg2k-0.1.0rc3.dist-info/top_level.txt
zarr_jpeg2k-0.1.0rc3.dist-info/RECORD
