Metadata-Version: 2.1
Name: zarr-jpeg2k
Version: 0.1.0rc3
Summary: JPEG-2000 Compression for zarr chunks
Home-page: https://github.com/glencoesoftware/zarr-jpeg2k
Author: Glencoe Software, Inc.
Author-email: info@glencoesoftware.com
License: UNKNOWN
Platform: UNKNOWN
Requires-Python: >=3.7
License-File: LICENSE
Requires-Dist: imagecodecs (==2021.8.26)
Requires-Dist: numcodecs (==0.9.1)
Requires-Dist: numpy (>=1.15)
